betfairlightweight/__init__.py
betfairlightweight/__version__.py
betfairlightweight/apiclient.py
betfairlightweight/baseclient.py
betfairlightweight/compat.py
betfairlightweight/enums.py
betfairlightweight/exceptions.py
betfairlightweight/filters.py
betfairlightweight/metadata.py
betfairlightweight/utils.py
betfairlightweight/endpoints/__init__.py
betfairlightweight/endpoints/account.py
betfairlightweight/endpoints/baseendpoint.py
betfairlightweight/endpoints/betting.py
betfairlightweight/endpoints/historic.py
betfairlightweight/endpoints/inplayservice.py
betfairlightweight/endpoints/keepalive.py
betfairlightweight/endpoints/login.py
betfairlightweight/endpoints/logininteractive.py
betfairlightweight/endpoints/logout.py
betfairlightweight/endpoints/navigation.py
betfairlightweight/endpoints/racecard.py
betfairlightweight/endpoints/scores.py
betfairlightweight/endpoints/streaming.py
betfairlightweight/resources/__init__.py
betfairlightweight/resources/accountresources.py
betfairlightweight/resources/authresources.py
betfairlightweight/resources/baseresource.py
betfairlightweight/resources/bettingresources.py
betfairlightweight/resources/inplayserviceresources.py
betfairlightweight/resources/racecardresources.py
betfairlightweight/resources/scoresresources.py
betfairlightweight/resources/streamingresources.py
betfairlightweight/streaming/__init__.py
betfairlightweight/streaming/betfairstream.py
betfairlightweight/streaming/cache.py
betfairlightweight/streaming/listener.py
betfairlightweight/streaming/stream.py
betfairlightweight-2.22.1.dist-info/METADATA
betfairlightweight-2.22.1.dist-info/WHEEL
betfairlightweight-2.22.1.dist-info/licenses/LICENSE
betfairlightweight-2.22.1.dist-info/RECORD
