Metadata-Version: 2.4
Name: betfairlightweight
Version: 2.22.1
Summary: Lightweight python wrapper for Betfair API-NG
Project-URL: Homepage, https://github.com/betcode-org
Project-URL: Documentation, https://betcode-org.github.io/betfair/
Project-URL: Repository, https://github.com/betcode-org/betfair.git
Project-URL: Bug Tracker, https://github.com/betcode-org/betfair/issues
Project-URL: Changelog, https://github.com/betcode-org/betfair/blob/master/HISTORY.rst
Author-email: Liam Pauling <a@unknown.com>
License: MIT License
License-File: LICENSE
Classifier: License :: OSI Approved :: MIT License
Classifier: Operating System :: OS Independent
Classifier: Programming Language :: Python :: 3.9
Classifier: Programming Language :: Python :: 3.10
Classifier: Programming Language :: Python :: 3.11
Classifier: Programming Language :: Python :: 3.12
Classifier: Programming Language :: Python :: 3.13
Classifier: Programming Language :: Python :: 3.14
Requires-Python: >=3.9
Requires-Dist: requests<2.33.0
Provides-Extra: speed
Requires-Dist: ciso8601==2.3.3; extra == 'speed'
Requires-Dist: orjson==3.11.4; extra == 'speed'
Provides-Extra: test
Requires-Dist: black==25.9.0; extra == 'test'
Requires-Dist: build; extra == 'test'
Requires-Dist: coverage; extra == 'test'
Requires-Dist: mkdocs; extra == 'test'
Requires-Dist: mkdocs-material; extra == 'test'
Requires-Dist: twine; extra == 'test'
